aither/__init__.py
aither/client.py
aither/extractors.py
aither/management.py
aither/models.py
aither/wrapper.py
aither-0.2.1.dist-info/METADATA
aither-0.2.1.dist-info/WHEEL
aither-0.2.1.dist-info/licenses/LICENSE
aither-0.2.1.dist-info/RECORD
