Metadata-Version: 2.4
Name: aither
Version: 0.2.1
Summary: aither - see through
Project-URL: Homepage, https://aither.computer
Project-URL: Repository, https://github.com/hyperprior/aither-sdk
Author: hyperprior
License-Expression: MIT
License-File: LICENSE
Keywords: machine-learning,ml,mlops,monitoring,observability
Classifier: Development Status :: 3 - Alpha
Classifier: Intended Audience :: Developers
Classifier: License :: OSI Approved :: MIT License
Classifier: Programming Language :: Python :: 3
Classifier: Programming Language :: Python :: 3.9
Classifier: Programming Language :: Python :: 3.10
Classifier: Programming Language :: Python :: 3.11
Classifier: Programming Language :: Python :: 3.12
Classifier: Programming Language :: Python :: 3.13
Classifier: Topic :: Scientific/Engineering :: Artificial Intelligence
Requires-Python: >=3.9
Requires-Dist: httpx>=0.24.0
Requires-Dist: opentelemetry-api>=1.20.0
Requires-Dist: opentelemetry-exporter-otlp-proto-http>=1.20.0
Requires-Dist: opentelemetry-sdk>=1.20.0
Requires-Dist: pydantic>=2.0.0
